pytest_asyncio_cooperative/__init__.py
pytest_asyncio_cooperative/assertion.py
pytest_asyncio_cooperative/fixtures.py
pytest_asyncio_cooperative/integration/__init__.py
pytest_asyncio_cooperative/integration/hypothesis.py
pytest_asyncio_cooperative/plugin.py
pytest_asyncio_cooperative-0.40.0.dist-info/LICENSE
pytest_asyncio_cooperative-0.40.0.dist-info/METADATA
pytest_asyncio_cooperative-0.40.0.dist-info/WHEEL
pytest_asyncio_cooperative-0.40.0.dist-info/entry_points.txt
pytest_asyncio_cooperative-0.40.0.dist-info/RECORD
