Metadata-Version: 2.3
Name: pytest-asyncio-cooperative
Version: 0.40.0
Summary: Run all your asynchronous tests cooperatively.
License: MIT
Author: Willem Thiart
Author-email: himself@willemthiart.com
Requires-Python: >=3.8
Classifier: License :: OSI Approved :: MIT License
Classifier: Programming Language :: Python :: 3
Classifier: Programming Language :: Python :: 3.8
Classifier: Programming Language :: Python :: 3.9
Classifier: Programming Language :: Python :: 3.10
Classifier: Programming Language :: Python :: 3.11
Classifier: Programming Language :: Python :: 3.12
Classifier: Programming Language :: Python :: 3.13
